django_oidc_admin/__init__.py
django_oidc_admin/apps.py
django_oidc_admin/authentication.py
django_oidc_admin/context_processors.py
django_oidc_admin/settings.py
django_oidc_admin/urls.py
django_oidc_admin/templates/admin/base.html
django_oidc_admin/templates/admin/login.html
django_oidc_admin/templatetags/__init__.py
django_oidc_admin/templatetags/django_oidc_admin.py
django_oidc_admin-0.1.4.dist-info/licenses/LICENSE
django_oidc_admin-0.1.4.dist-info/METADATA
django_oidc_admin-0.1.4.dist-info/WHEEL
django_oidc_admin-0.1.4.dist-info/top_level.txt
django_oidc_admin-0.1.4.dist-info/RECORD
