Metadata-Version: 2.4
Name: django-oidc-admin
Version: 0.1.4
Summary: A Django sso login based on django-mozilla-oidc that creates an inactive user upon SSO login.
Author-email: Camille-cmd <perso@camillemeunier.fr>
License: MIT
Project-URL: Repository, https://github.com/Camille-cmd/django-oidc-admin
Classifier: Environment :: Web Environment
Classifier: Framework :: Django
Classifier: Framework :: Django :: 5.0
Classifier: Intended Audience :: Developers
Classifier: License :: OSI Approved :: MIT License
Classifier: Operating System :: OS Independent
Classifier: Programming Language :: Python
Classifier: Programming Language :: Python :: 3
Classifier: Programming Language :: Python :: 3 :: Only
Classifier: Programming Language :: Python :: 3.10
Classifier: Programming Language :: Python :: 3.11
Classifier: Programming Language :: Python :: 3.12
Classifier: Programming Language :: Python :: 3.13
Requires-Python: >=3.10
License-File: LICENSE
Requires-Dist: django>=5.0
Requires-Dist: mozilla-django-oidc>=4.0.1
Dynamic: license-file
